fustor_event_model/__init__.py
fustor_event_model/models.py
fustor_event_model-0.2.16.dist-info/METADATA
fustor_event_model-0.2.16.dist-info/WHEEL
fustor_event_model-0.2.16.dist-info/top_level.txt
fustor_event_model-0.2.16.dist-info/RECORD
