Metadata-Version: 2.4
Name: fustor-event-model
Version: 0.2.16
Summary: Event models and schemas for Fustor services
License-Expression: MIT
Requires-Python: >=3.11
Requires-Dist: pydantic>=2.11.7
